{
    "Ar36": {
        "error": 0.0003598078068049998,
        "error_type": "SEM",
        "filter_outliers_dict": {
            "filter_outliers": true,
            "iterations": 1,
            "std_devs": 3,
            "use_iqr_filtering": false,
            "use_standard_deviation_filtering": false
        },
        "fit": "linear",
        "fn": 237,
        "include_baseline_error": false,
        "n": 240,
        "outlier_excluded": [
            2,
            4,
            181
        ],
        "reviewed": true,
        "user_excluded": [],
        "value": 0.032945183522559734
    },
    "Ar37": {
        "error": 0.004353155991496682,
        "error_type": "SEM",
        "filter_outliers_dict": {
            "filter_outliers": true,
            "iterations": 1,
            "std_devs": 3,
            "use_iqr_filtering": false,
            "use_standard_deviation_filtering": false
        },
        "fit": "linear",
        "fn": 240,
        "include_baseline_error": false,
        "n": 240,
        "outlier_excluded": [],
        "reviewed": true,
        "user_excluded": [],
        "value": 0.13976793788894337
    },
    "Ar38": {
        "error": 0.0036669723491488003,
        "error_type": "SEM",
        "filter_outliers_dict": {
            "filter_outliers": true,
            "iterations": 1,
            "std_devs": 3,
            "use_iqr_filtering": false,
            "use_standard_deviation_filtering": false
        },
        "fit": "linear",
        "fn": 240,
        "include_baseline_error": false,
        "n": 240,
        "outlier_excluded": [],
        "reviewed": true,
        "user_excluded": [],
        "value": 0.37791238664683435
    },
    "Ar39": {
        "error": 0.01723245833295956,
        "error_type": "SEM",
        "filter_outliers_dict": {
            "filter_outliers": true,
            "iterations": 1,
            "std_devs": 3,
            "use_iqr_filtering": false,
            "use_standard_deviation_filtering": false
        },
        "fit": "parabolic",
        "fn": 239,
        "include_baseline_error": false,
        "n": 240,
        "outlier_excluded": [
            41
        ],
        "reviewed": true,
        "user_excluded": [],
        "value": 23.86546501604931
    },
    "Ar40": {
        "error": 0.05723662702995583,
        "error_type": "SEM",
        "filter_outliers_dict": {
            "filter_outliers": true,
            "iterations": 1,
            "std_devs": 3,
            "use_iqr_filtering": false,
            "use_standard_deviation_filtering": false
        },
        "fit": "parabolic",
        "fn": 239,
        "include_baseline_error": false,
        "n": 240,
        "outlier_excluded": [
            39
        ],
        "reviewed": true,
        "user_excluded": [],
        "value": 592.6490998297595
    },
    "Ar41": {
        "error": 0.003281653738369038,
        "error_type": "SEM",
        "filter_outliers_dict": {
            "filter_outliers": true,
            "iterations": 1,
            "std_devs": 3
        },
        "fit": "average",
        "value": 0.15646790587060672
    }
}