{
    "Ar36": {
        "error": 0.0003189088920817764,
        "error_type": "SEM",
        "filter_outliers_dict": {
            "filter_outliers": true,
            "iterations": 1,
            "std_devs": 3,
            "use_iqr_filtering": false,
            "use_standard_deviation_filtering": false
        },
        "fit": "linear",
        "fn": 237,
        "include_baseline_error": false,
        "n": 240,
        "outlier_excluded": [
            0,
            1,
            4
        ],
        "reviewed": true,
        "user_excluded": [],
        "value": 0.019994235184675573
    },
    "Ar37": {
        "error": 0.004362356924890225,
        "error_type": "SEM",
        "filter_outliers_dict": {
            "filter_outliers": true,
            "iterations": 1,
            "std_devs": 3,
            "use_iqr_filtering": false,
            "use_standard_deviation_filtering": false
        },
        "fit": "linear",
        "fn": 239,
        "include_baseline_error": false,
        "n": 240,
        "outlier_excluded": [
            0
        ],
        "reviewed": true,
        "user_excluded": [],
        "value": 0.05619452819952671
    },
    "Ar38": {
        "error": 0.003381898511874931,
        "error_type": "SEM",
        "filter_outliers_dict": {
            "filter_outliers": true,
            "iterations": 1,
            "std_devs": 3,
            "use_iqr_filtering": false,
            "use_standard_deviation_filtering": false
        },
        "fit": "linear",
        "fn": 239,
        "include_baseline_error": false,
        "n": 240,
        "outlier_excluded": [
            1
        ],
        "reviewed": true,
        "user_excluded": [],
        "value": 0.15840455920889127
    },
    "Ar39": {
        "error": 0.01573790223007436,
        "error_type": "SEM",
        "filter_outliers_dict": {
            "filter_outliers": true,
            "iterations": 1,
            "std_devs": 3,
            "use_iqr_filtering": false,
            "use_standard_deviation_filtering": false
        },
        "fit": "parabolic",
        "fn": 239,
        "include_baseline_error": false,
        "n": 240,
        "outlier_excluded": [
            28
        ],
        "reviewed": true,
        "user_excluded": [],
        "value": 5.2690180322993525
    },
    "Ar40": {
        "error": 0.026444948901291294,
        "error_type": "SEM",
        "filter_outliers_dict": {
            "filter_outliers": true,
            "iterations": 1,
            "std_devs": 3,
            "use_iqr_filtering": false,
            "use_standard_deviation_filtering": false
        },
        "fit": "parabolic",
        "fn": 240,
        "include_baseline_error": false,
        "n": 240,
        "outlier_excluded": [],
        "reviewed": true,
        "user_excluded": [],
        "value": 128.86550534317087
    },
    "Ar41": {
        "error": 0.003800759431736974,
        "error_type": "SEM",
        "filter_outliers_dict": {
            "filter_outliers": true,
            "iterations": 1,
            "std_devs": 3
        },
        "fit": "average",
        "value": 0.09003435451406099
    }
}