{
    "AX(CDD)": {
        "error": 0.0,
        "error_type": "SEM",
        "filter_outliers_dict": {
            "filter_outliers": true,
            "iterations": 1,
            "std_devs": 2
        },
        "fit": "average",
        "modifier_error": 2.518814686820998e-05,
        "modifier_value": 0.00025237844431275563,
        "value": 0.00025237844431275563
    },
    "H1": {
        "error": 0.008306727245920357,
        "error_type": "SEM",
        "filter_outliers_dict": {
            "filter_outliers": true,
            "iterations": 1,
            "std_devs": 2
        },
        "fit": "average",
        "modifier_error": 0.0,
        "modifier_value": 0.0,
        "value": -0.016096284022031938
    },
    "H2": {
        "error": 0.014986233969718233,
        "error_type": "SEM",
        "filter_outliers_dict": {
            "filter_outliers": true,
            "iterations": 1,
            "std_devs": 2
        },
        "fit": "average",
        "modifier_error": 0.0,
        "modifier_value": 0.0,
        "value": -0.46869599099293674
    },
    "L1": {
        "error": 0.007339983935624673,
        "error_type": "SEM",
        "filter_outliers_dict": {
            "filter_outliers": true,
            "iterations": 1,
            "std_devs": 2
        },
        "fit": "average",
        "modifier_error": 0.0,
        "modifier_value": 0.0,
        "value": -0.010494578956377145
    },
    "L2(CDD)": {
        "error": 4.410971878716598e-22,
        "error_type": "SEM",
        "filter_outliers_dict": {
            "filter_outliers": true,
            "iterations": 1,
            "std_devs": 10
        },
        "fit": "average",
        "modifier_error": 6.664157259985401e-06,
        "modifier_value": 1.7666491101892893e-05,
        "value": 1.766649110189289e-05
    }
}