{
    "Ar36": {
        "error": 0.0005577921325564427,
        "error_type": "SEM",
        "filter_outliers_dict": {
            "filter_outliers": true,
            "iterations": 1,
            "std_devs": 3,
            "use_iqr_filtering": false,
            "use_standard_deviation_filtering": false
        },
        "fit": "linear",
        "fn": 180,
        "include_baseline_error": false,
        "n": 180,
        "outlier_excluded": [],
        "reviewed": true,
        "user_excluded": [],
        "value": 0.06738677244544788
    },
    "Ar37": {
        "error": 0.0053326642759672915,
        "error_type": "SEM",
        "filter_outliers_dict": {
            "filter_outliers": true,
            "iterations": 1,
            "std_devs": 3,
            "use_iqr_filtering": false,
            "use_standard_deviation_filtering": false
        },
        "fit": "linear",
        "fn": 179,
        "include_baseline_error": false,
        "n": 180,
        "outlier_excluded": [
            175
        ],
        "reviewed": true,
        "user_excluded": [],
        "value": 0.11310995566322678
    },
    "Ar38": {
        "error": 0.004570328924005971,
        "error_type": "SEM",
        "filter_outliers_dict": {
            "filter_outliers": true,
            "iterations": 1,
            "std_devs": 3,
            "use_iqr_filtering": false,
            "use_standard_deviation_filtering": false
        },
        "fit": "linear",
        "fn": 179,
        "include_baseline_error": false,
        "n": 180,
        "outlier_excluded": [
            91
        ],
        "reviewed": true,
        "user_excluded": [],
        "value": 0.7013710715906133
    },
    "Ar39": {
        "error": 0.026309631304561924,
        "error_type": "SEM",
        "filter_outliers_dict": {
            "filter_outliers": true,
            "iterations": 1,
            "std_devs": 3,
            "use_iqr_filtering": false,
            "use_standard_deviation_filtering": false
        },
        "fit": "parabolic",
        "fn": 180,
        "include_baseline_error": false,
        "n": 180,
        "outlier_excluded": [],
        "reviewed": true,
        "user_excluded": [],
        "value": 51.67516123436462
    },
    "Ar40": {
        "error": 0.11622277063519607,
        "error_type": "SEM",
        "filter_outliers_dict": {
            "filter_outliers": true,
            "iterations": 1,
            "std_devs": 3,
            "use_iqr_filtering": false,
            "use_standard_deviation_filtering": false
        },
        "fit": "parabolic",
        "fn": 180,
        "include_baseline_error": false,
        "n": 180,
        "outlier_excluded": [],
        "reviewed": true,
        "user_excluded": [],
        "value": 1212.3931887250405
    },
    "Ar41": {
        "error": 0.0039947258900806665,
        "error_type": "SEM",
        "filter_outliers_dict": {
            "filter_outliers": true,
            "iterations": 1,
            "std_devs": 3
        },
        "fit": "average",
        "value": 0.2121430989198163
    }
}