{
    "Ar36": {
        "error": 0.0004629662568603627,
        "error_type": "SEM",
        "filter_outliers_dict": {
            "filter_outliers": true,
            "iterations": 1,
            "std_devs": 3,
            "use_iqr_filtering": false,
            "use_standard_deviation_filtering": false
        },
        "fit": "linear",
        "fn": 240,
        "include_baseline_error": false,
        "n": 240,
        "outlier_excluded": [],
        "reviewed": true,
        "user_excluded": [],
        "value": 0.05415482105184387
    },
    "Ar37": {
        "error": 0.004293550155983176,
        "error_type": "SEM",
        "filter_outliers_dict": {
            "filter_outliers": true,
            "iterations": 1,
            "std_devs": 3,
            "use_iqr_filtering": false,
            "use_standard_deviation_filtering": false
        },
        "fit": "linear",
        "fn": 240,
        "include_baseline_error": false,
        "n": 240,
        "outlier_excluded": [],
        "reviewed": true,
        "user_excluded": [],
        "value": 0.18511041130258354
    },
    "Ar38": {
        "error": 0.0038121462059034126,
        "error_type": "SEM",
        "filter_outliers_dict": {
            "filter_outliers": true,
            "iterations": 1,
            "std_devs": 3,
            "use_iqr_filtering": false,
            "use_standard_deviation_filtering": false
        },
        "fit": "linear",
        "fn": 239,
        "include_baseline_error": false,
        "n": 240,
        "outlier_excluded": [
            200
        ],
        "reviewed": true,
        "user_excluded": [],
        "value": 0.616295730169561
    },
    "Ar39": {
        "error": 0.01904425528410547,
        "error_type": "SEM",
        "filter_outliers_dict": {
            "filter_outliers": true,
            "iterations": 1,
            "std_devs": 3,
            "use_iqr_filtering": false,
            "use_standard_deviation_filtering": false
        },
        "fit": "parabolic",
        "fn": 239,
        "include_baseline_error": false,
        "n": 240,
        "outlier_excluded": [
            170
        ],
        "reviewed": true,
        "user_excluded": [],
        "value": 44.501823752700886
    },
    "Ar40": {
        "error": 0.09224749147658727,
        "error_type": "SEM",
        "filter_outliers_dict": {
            "filter_outliers": true,
            "iterations": 1,
            "std_devs": 3,
            "use_iqr_filtering": false,
            "use_standard_deviation_filtering": false
        },
        "fit": "parabolic",
        "fn": 240,
        "include_baseline_error": false,
        "n": 240,
        "outlier_excluded": [],
        "reviewed": true,
        "user_excluded": [],
        "value": 1031.2041122965443
    },
    "Ar41": {
        "error": 0.0031094458494840094,
        "error_type": "SEM",
        "filter_outliers_dict": {
            "filter_outliers": true,
            "iterations": 1,
            "std_devs": 3
        },
        "fit": "average",
        "value": 0.2249408278870413
    }
}